chia_py_rpc/__init__.py
chia_py_rpc/rpc_connect.py
chia_py_rpc/wallet.py
chia_py_rpc-0.1.1.dist-info/METADATA
chia_py_rpc-0.1.1.dist-info/WHEEL
chia_py_rpc-0.1.1.dist-info/licenses/LICENSE
chia_py_rpc-0.1.1.dist-info/RECORD
