Metadata-Version: 2.1
Name: chia_py_rpc
Version: 0.1.1
Summary: Chia-Py-RPC is a Python library that provides a convenient way to interact with the Chia blockchain using the Chia RPC (Remote Procedure Call) protocol.
Project-URL: Homepage, https://github.com/L4bb3rs/Chia-Py-RPC
Project-URL: Bug Tracker, https://github.com/L4bb3rs/Chia-Py-RPC
Author-email: L4bb3rs <king@the300.net>
License-File: LICENSE
Classifier: License :: OSI Approved :: MIT License
Classifier: Operating System :: OS Independent
Classifier: Programming Language :: Python :: 3
Requires-Python: >=3.11
Requires-Dist: requests>=2.31.0
Requires-Dist: urllib3>=2.0.7
